[
  {
    "autopatch_effective": false,
    "batch_size": 1,
    "cce_installed": false,
    "chips": 4,
    "default_ce": true,
    "final_loss": 1.585516333580017,
    "first_step_time_sec": "88.77675922599997",
    "gemma3_activation_policy_installed": false,
    "gemma3_splash_attention_installed": false,
    "gemma3_tiled_mlp_installed": false,
    "lora_rank": 16,
    "loss_tokens_per_sec_excl_first": 71.77151912395846,
    "max_length": 512,
    "max_steps": 2,
    "mean_loss": 2.061228930950165,
    "mean_step_time_sec_excl_first": 0.34832758599998215,
    "mesh_fsdp": 4,
    "mesh_tp": 1,
    "model_id": "google/gemma-3-12b-it",
    "model_size": "12b",
    "requested_autopatch": false,
    "run_dir": "/tmp/gemma3-large-patch-sweep-corrected/12b/default_b1_l512",
    "runtime_hbm_headroom_gb_aggregate": 18.685923328,
    "runtime_hbm_limit_gb_aggregate": 67.637338112,
    "runtime_peak_hbm_gb_aggregate": 48.951414784,
    "second_step_time_sec": "0.34832758599998215",
    "status": "ok",
    "steps_recorded": 2,
    "tpu": "v5litepod-4",
    "valid_tokens_per_sec_excl_first": 177.99336742741696,
    "variant": "default",
    "wall_time_sec": 121.17055851599997,
    "xla_report": "/tmp/gemma3-large-patch-sweep-corrected/12b/default_b1_l512/xla/module_0676.jit__train_step.cl_914450892.after_optimizations-memory-usage-report.txt",
    "xla_train_step_gib_per_chip": 12.39
  },
  {
    "autopatch_effective": true,
    "batch_size": 1,
    "cce_installed": true,
    "chips": 4,
    "default_ce": false,
    "final_loss": 1.5772923231124878,
    "first_step_time_sec": "87.61790352600002",
    "gemma3_activation_policy_installed": false,
    "gemma3_splash_attention_installed": false,
    "gemma3_tiled_mlp_installed": false,
    "lora_rank": 16,
    "loss_tokens_per_sec_excl_first": 69.17556344888112,
    "max_length": 512,
    "max_steps": 2,
    "mean_loss": 2.0551698803901672,
    "mean_step_time_sec_excl_first": 0.36139929699993445,
    "mesh_fsdp": 4,
    "mesh_tp": 1,
    "model_id": "google/gemma-3-12b-it",
    "model_size": "12b",
    "requested_autopatch": true,
    "run_dir": "/tmp/gemma3-large-patch-sweep-corrected/12b/cce_b1_l512",
    "runtime_hbm_headroom_gb_aggregate": 18.6246144,
    "runtime_hbm_limit_gb_aggregate": 67.637338112,
    "runtime_peak_hbm_gb_aggregate": 49.012723712,
    "second_step_time_sec": "0.36139929699993445",
    "status": "ok",
    "steps_recorded": 2,
    "tpu": "v5litepod-4",
    "valid_tokens_per_sec_excl_first": 171.5553973532252,
    "variant": "cce",
    "wall_time_sec": 122.37216097700002,
    "xla_report": "/tmp/gemma3-large-patch-sweep-corrected/12b/cce_b1_l512/xla/module_0676.jit__train_step.cl_914450892.after_optimizations-memory-usage-report.txt",
    "xla_train_step_gib_per_chip": 12.23
  },
  {
    "autopatch_effective": true,
    "batch_size": 1,
    "cce_installed": false,
    "chips": 4,
    "default_ce": false,
    "final_loss": 1.8835046291351318,
    "first_step_time_sec": "56.57209265999995",
    "gemma3_activation_policy_installed": false,
    "gemma3_splash_attention_installed": false,
    "gemma3_tiled_mlp_installed": true,
    "lora_rank": 16,
    "loss_tokens_per_sec_excl_first": 87.82932466007794,
    "max_length": 512,
    "max_steps": 2,
    "mean_loss": 2.1960591077804565,
    "mean_step_time_sec_excl_first": 0.28464297200002875,
    "mesh_fsdp": 4,
    "mesh_tp": 1,
    "model_id": "google/gemma-3-12b-it",
    "model_size": "12b",
    "requested_autopatch": true,
    "run_dir": "/tmp/gemma3-large-patch-sweep-corrected/12b/tiled_mlp_b1_l512",
    "runtime_hbm_headroom_gb_aggregate": 19.98522368,
    "runtime_hbm_limit_gb_aggregate": 67.637338112,
    "runtime_peak_hbm_gb_aggregate": 47.652114432,
    "second_step_time_sec": "0.28464297200002875",
    "status": "ok",
    "steps_recorded": 2,
    "tpu": "v5litepod-4",
    "valid_tokens_per_sec_excl_first": 217.8167251569933,
    "variant": "tiled_mlp",
    "wall_time_sec": 93.8563751339999,
    "xla_report": "/tmp/gemma3-large-patch-sweep-corrected/12b/tiled_mlp_b1_l512/xla/module_0634.jit__train_step.cl_914450892.after_optimizations-memory-usage-report.txt",
    "xla_train_step_gib_per_chip": 11.78
  },
  {
    "autopatch_effective": true,
    "batch_size": 1,
    "cce_installed": false,
    "chips": 4,
    "default_ce": false,
    "final_loss": 1.567293643951416,
    "first_step_time_sec": "98.01404665899997",
    "gemma3_activation_policy_installed": true,
    "gemma3_splash_attention_installed": false,
    "gemma3_tiled_mlp_installed": false,
    "lora_rank": 16,
    "loss_tokens_per_sec_excl_first": 0.27662286519336665,
    "max_length": 512,
    "max_steps": 2,
    "mean_loss": 2.0583813190460205,
    "mean_step_time_sec_excl_first": 90.37575394400005,
    "mesh_fsdp": 4,
    "mesh_tp": 1,
    "model_id": "google/gemma-3-12b-it",
    "model_size": "12b",
    "requested_autopatch": true,
    "run_dir": "/tmp/gemma3-large-patch-sweep-corrected/12b/split_offload_b1_l512",
    "runtime_hbm_headroom_gb_aggregate": 18.332004352,
    "runtime_hbm_limit_gb_aggregate": 67.637338112,
    "runtime_peak_hbm_gb_aggregate": 49.30533376,
    "second_step_time_sec": "90.37575394400005",
    "status": "ok",
    "steps_recorded": 2,
    "tpu": "v5litepod-4",
    "valid_tokens_per_sec_excl_first": 0.6860247056795493,
    "variant": "split_offload",
    "wall_time_sec": 225.42097411500004,
    "xla_report": "/tmp/gemma3-large-patch-sweep-corrected/12b/split_offload_b1_l512/xla/module_1013.jit__train_step.cl_914450892.after_optimizations-memory-usage-report.txt",
    "xla_train_step_gib_per_chip": 12.04
  },
  {
    "autopatch_effective": true,
    "batch_size": 1,
    "cce_installed": false,
    "chips": 4,
    "default_ce": false,
    "final_loss": 1.6387231349945068,
    "first_step_time_sec": "87.16470756700005",
    "gemma3_activation_policy_installed": false,
    "gemma3_splash_attention_installed": true,
    "gemma3_tiled_mlp_installed": false,
    "lora_rank": 16,
    "loss_tokens_per_sec_excl_first": 68.52346415131738,
    "max_length": 512,
    "max_steps": 2,
    "mean_loss": 2.1014190912246704,
    "mean_step_time_sec_excl_first": 0.36483853100003216,
    "mesh_fsdp": 4,
    "mesh_tp": 1,
    "model_id": "google/gemma-3-12b-it",
    "model_size": "12b",
    "requested_autopatch": true,
    "run_dir": "/tmp/gemma3-large-patch-sweep-corrected/12b/splash_b1_l512",
    "runtime_hbm_headroom_gb_aggregate": 18.694694912,
    "runtime_hbm_limit_gb_aggregate": 67.637338112,
    "runtime_peak_hbm_gb_aggregate": 48.9426432,
    "second_step_time_sec": "0.36483853100003216",
    "status": "ok",
    "steps_recorded": 2,
    "tpu": "v5litepod-4",
    "valid_tokens_per_sec_excl_first": 169.93819109526711,
    "variant": "splash",
    "wall_time_sec": 128.6442674330001,
    "xla_report": "/tmp/gemma3-large-patch-sweep-corrected/12b/splash_b1_l512/xla/module_0676.jit__train_step.cl_914450892.after_optimizations-memory-usage-report.txt",
    "xla_train_step_gib_per_chip": 12.46
  },
  {
    "autopatch_effective": true,
    "batch_size": 1,
    "cce_installed": true,
    "chips": 4,
    "default_ce": false,
    "final_loss": 1.6932767629623413,
    "first_step_time_sec": "76.44017498500011",
    "gemma3_activation_policy_installed": true,
    "gemma3_splash_attention_installed": true,
    "gemma3_tiled_mlp_installed": true,
    "lora_rank": 16,
    "loss_tokens_per_sec_excl_first": 0.36608445714869026,
    "max_length": 512,
    "max_steps": 2,
    "mean_loss": 2.110953390598297,
    "mean_step_time_sec_excl_first": 68.29025245899993,
    "mesh_fsdp": 4,
    "mesh_tp": 1,
    "model_id": "google/gemma-3-12b-it",
    "model_size": "12b",
    "requested_autopatch": true,
    "run_dir": "/tmp/gemma3-large-patch-sweep-corrected/12b/stacked_b1_l512",
    "runtime_hbm_headroom_gb_aggregate": 19.796283392,
    "runtime_hbm_limit_gb_aggregate": 67.637338112,
    "runtime_peak_hbm_gb_aggregate": 47.84105472,
    "second_step_time_sec": "68.29025245899993",
    "status": "ok",
    "steps_recorded": 2,
    "tpu": "v5litepod-4",
    "valid_tokens_per_sec_excl_first": 0.9078894537287518,
    "variant": "stacked",
    "wall_time_sec": 179.23322084100005,
    "xla_report": "/tmp/gemma3-large-patch-sweep-corrected/12b/stacked_b1_l512/xla/module_0979.jit__train_step.cl_914450892.after_optimizations-memory-usage-report.txt",
    "xla_train_step_gib_per_chip": 11.74
  },
  {
    "batch_size": 1,
    "chips": 4,
    "failure_type": "compile_oom",
    "lora_rank": 16,
    "max_length": 1024,
    "max_steps": 2,
    "mesh_fsdp": 4,
    "mesh_tp": 1,
    "model_id": "google/gemma-3-12b-it",
    "model_size": "12b",
    "oom_exceeded_gib": "1.67",
    "oom_limit_gib": "15.75",
    "oom_used_gib": "17.42",
    "requested_autopatch": false,
    "run_dir": "/tmp/gemma3-large-patch-sweep-corrected/12b/default_b1_l1024",
    "status": "failed",
    "tpu": "v5litepod-4",
    "variant": "default",
    "xla_report": "/tmp/gemma3-large-patch-sweep-corrected/12b/default_b1_l1024/xla/module_0676.jit__train_step.cl_914450892.after_optimizations-memory-usage-report.txt",
    "xla_train_step_gib_per_chip": 17.42
  },
  {
    "batch_size": 1,
    "chips": 4,
    "failure_type": "compile_oom",
    "lora_rank": 16,
    "max_length": 1024,
    "max_steps": 2,
    "mesh_fsdp": 4,
    "mesh_tp": 1,
    "model_id": "google/gemma-3-12b-it",
    "model_size": "12b",
    "requested_autopatch": true,
    "run_dir": "/tmp/gemma3-large-patch-sweep-corrected/12b/cce_b1_l1024",
    "status": "failed",
    "tpu": "v5litepod-4",
    "variant": "cce",
    "xla_report": "/tmp/gemma3-large-patch-sweep-corrected/12b/cce_b1_l1024/xla/module_0676.jit__train_step.cl_914450892.after_optimizations-memory-usage-report.txt",
    "xla_train_step_gib_per_chip": 16.5
  },
  {
    "autopatch_effective": true,
    "batch_size": 1,
    "cce_installed": false,
    "chips": 4,
    "default_ce": false,
    "final_loss": 1.8081921339035034,
    "first_step_time_sec": "60.45841997100001",
    "gemma3_activation_policy_installed": false,
    "gemma3_splash_attention_installed": false,
    "gemma3_tiled_mlp_installed": true,
    "lora_rank": 16,
    "loss_tokens_per_sec_excl_first": 57.44083604226936,
    "max_length": 1024,
    "max_steps": 2,
    "mean_loss": 2.160275876522064,
    "mean_step_time_sec_excl_first": 0.4352304340000046,
    "mesh_fsdp": 4,
    "mesh_tp": 1,
    "model_id": "google/gemma-3-12b-it",
    "model_size": "12b",
    "requested_autopatch": true,
    "run_dir": "/tmp/gemma3-large-patch-sweep-corrected/12b/tiled_mlp_b1_l1024",
    "runtime_hbm_headroom_gb_aggregate": 19.943847936,
    "runtime_hbm_limit_gb_aggregate": 67.637338112,
    "runtime_peak_hbm_gb_aggregate": 47.693490176,
    "second_step_time_sec": "0.4352304340000046",
    "status": "ok",
    "steps_recorded": 2,
    "tpu": "v5litepod-4",
    "valid_tokens_per_sec_excl_first": 142.453273384828,
    "variant": "tiled_mlp",
    "wall_time_sec": 92.21617495199985,
    "xla_report": "/tmp/gemma3-large-patch-sweep-corrected/12b/tiled_mlp_b1_l1024/xla/module_0634.jit__train_step.cl_914450892.after_optimizations-memory-usage-report.txt",
    "xla_train_step_gib_per_chip": 14.13
  },
  {
    "autopatch_effective": true,
    "batch_size": 1,
    "cce_installed": false,
    "chips": 4,
    "default_ce": false,
    "final_loss": 1.544836401939392,
    "first_step_time_sec": "100.43549501500001",
    "gemma3_activation_policy_installed": true,
    "gemma3_splash_attention_installed": false,
    "gemma3_tiled_mlp_installed": false,
    "lora_rank": 16,
    "loss_tokens_per_sec_excl_first": 0.2644528151710486,
    "max_length": 1024,
    "max_steps": 2,
    "mean_loss": 2.03352028131485,
    "mean_step_time_sec_excl_first": 94.53482271999997,
    "mesh_fsdp": 4,
    "mesh_tp": 1,
    "model_id": "google/gemma-3-12b-it",
    "model_size": "12b",
    "requested_autopatch": true,
    "run_dir": "/tmp/gemma3-large-patch-sweep-corrected/12b/split_offload_b1_l1024",
    "runtime_hbm_headroom_gb_aggregate": 18.2876672,
    "runtime_hbm_limit_gb_aggregate": 67.637338112,
    "runtime_peak_hbm_gb_aggregate": 49.349670912,
    "second_step_time_sec": "94.53482271999997",
    "status": "ok",
    "steps_recorded": 2,
    "tpu": "v5litepod-4",
    "valid_tokens_per_sec_excl_first": 0.6558429816242006,
    "variant": "split_offload",
    "wall_time_sec": 230.93660397000008,
    "xla_report": "/tmp/gemma3-large-patch-sweep-corrected/12b/split_offload_b1_l1024/xla/module_1024.jit__train_step.cl_914450892.after_optimizations-memory-usage-report.txt",
    "xla_train_step_gib_per_chip": 12.58
  },
  {
    "batch_size": 1,
    "chips": 4,
    "failure_type": "compile_oom",
    "lora_rank": 16,
    "max_length": 1024,
    "max_steps": 2,
    "mesh_fsdp": 4,
    "mesh_tp": 1,
    "model_id": "google/gemma-3-12b-it",
    "model_size": "12b",
    "requested_autopatch": true,
    "run_dir": "/tmp/gemma3-large-patch-sweep-corrected/12b/splash_b1_l1024",
    "status": "failed",
    "tpu": "v5litepod-4",
    "variant": "splash",
    "xla_report": "/tmp/gemma3-large-patch-sweep-corrected/12b/splash_b1_l1024/xla/module_0676.jit__train_step.cl_914450892.after_optimizations-memory-usage-report.txt",
    "xla_train_step_gib_per_chip": 16.52
  },
  {
    "autopatch_effective": true,
    "batch_size": 1,
    "cce_installed": true,
    "chips": 4,
    "default_ce": false,
    "final_loss": 1.7125322818756104,
    "first_step_time_sec": "76.21218440899975",
    "gemma3_activation_policy_installed": true,
    "gemma3_splash_attention_installed": true,
    "gemma3_tiled_mlp_installed": true,
    "lora_rank": 16,
    "loss_tokens_per_sec_excl_first": 0.36359226727724747,
    "max_length": 1024,
    "max_steps": 2,
    "mean_loss": 2.1378332376480103,
    "mean_step_time_sec_excl_first": 68.75833797900032,
    "mesh_fsdp": 4,
    "mesh_tp": 1,
    "model_id": "google/gemma-3-12b-it",
    "model_size": "12b",
    "requested_autopatch": true,
    "run_dir": "/tmp/gemma3-large-patch-sweep-corrected/12b/stacked_b1_l1024",
    "runtime_hbm_headroom_gb_aggregate": 19.776815104,
    "runtime_hbm_limit_gb_aggregate": 67.637338112,
    "runtime_peak_hbm_gb_aggregate": 47.860523008,
    "second_step_time_sec": "68.75833797900032",
    "status": "ok",
    "steps_recorded": 2,
    "tpu": "v5litepod-4",
    "valid_tokens_per_sec_excl_first": 0.9017088228475738,
    "variant": "stacked",
    "wall_time_sec": 177.36714361099985,
    "xla_report": "/tmp/gemma3-large-patch-sweep-corrected/12b/stacked_b1_l1024/xla/module_0978.jit__train_step.cl_914450892.after_optimizations-memory-usage-report.txt",
    "xla_train_step_gib_per_chip": 11.74
  },
  {
    "batch_size": 1,
    "chips": 4,
    "failure_type": "compile_oom",
    "lora_rank": 16,
    "max_length": 2048,
    "max_steps": 2,
    "mesh_fsdp": 4,
    "mesh_tp": 1,
    "model_id": "google/gemma-3-12b-it",
    "model_size": "12b",
    "oom_exceeded_gib": "10.76",
    "oom_limit_gib": "15.75",
    "oom_used_gib": "26.51",
    "requested_autopatch": false,
    "run_dir": "/tmp/gemma3-large-patch-sweep-corrected/12b/default_b1_l2048",
    "status": "failed",
    "tpu": "v5litepod-4",
    "variant": "default",
    "xla_report": "/tmp/gemma3-large-patch-sweep-corrected/12b/default_b1_l2048/xla/module_0676.jit__train_step.cl_914450892.after_optimizations-memory-usage-report.txt",
    "xla_train_step_gib_per_chip": 26.51
  },
  {
    "batch_size": 1,
    "chips": 4,
    "failure_type": "compile_oom",
    "lora_rank": 16,
    "max_length": 2048,
    "max_steps": 2,
    "mesh_fsdp": 4,
    "mesh_tp": 1,
    "model_id": "google/gemma-3-12b-it",
    "model_size": "12b",
    "oom_exceeded_gib": "8.96",
    "oom_limit_gib": "15.75",
    "oom_used_gib": "24.71",
    "requested_autopatch": true,
    "run_dir": "/tmp/gemma3-large-patch-sweep-corrected/12b/cce_b1_l2048",
    "status": "failed",
    "tpu": "v5litepod-4",
    "variant": "cce",
    "xla_report": "/tmp/gemma3-large-patch-sweep-corrected/12b/cce_b1_l2048/xla/module_0676.jit__train_step.cl_914450892.after_optimizations-memory-usage-report.txt",
    "xla_train_step_gib_per_chip": 24.71
  },
  {
    "batch_size": 1,
    "chips": 4,
    "failure_type": "compile_oom",
    "lora_rank": 16,
    "max_length": 2048,
    "max_steps": 2,
    "mesh_fsdp": 4,
    "mesh_tp": 1,
    "model_id": "google/gemma-3-12b-it",
    "model_size": "12b",
    "oom_exceeded_gib": "4.68",
    "oom_limit_gib": "15.75",
    "oom_used_gib": "20.42",
    "requested_autopatch": true,
    "run_dir": "/tmp/gemma3-large-patch-sweep-corrected/12b/tiled_mlp_b1_l2048",
    "status": "failed",
    "tpu": "v5litepod-4",
    "variant": "tiled_mlp",
    "xla_report": "/tmp/gemma3-large-patch-sweep-corrected/12b/tiled_mlp_b1_l2048/xla/module_0634.jit__train_step.cl_914450892.after_optimizations-memory-usage-report.txt",
    "xla_train_step_gib_per_chip": 20.42
  },
  {
    "autopatch_effective": true,
    "batch_size": 1,
    "cce_installed": false,
    "chips": 4,
    "default_ce": false,
    "final_loss": 1.6184117794036865,
    "first_step_time_sec": "108.15517617400019",
    "gemma3_activation_policy_installed": true,
    "gemma3_splash_attention_installed": false,
    "gemma3_tiled_mlp_installed": false,
    "lora_rank": 16,
    "loss_tokens_per_sec_excl_first": 0.24785933480226152,
    "max_length": 2048,
    "max_steps": 2,
    "mean_loss": 2.0707606077194214,
    "mean_step_time_sec_excl_first": 100.86366131799969,
    "mesh_fsdp": 4,
    "mesh_tp": 1,
    "model_id": "google/gemma-3-12b-it",
    "model_size": "12b",
    "requested_autopatch": true,
    "run_dir": "/tmp/gemma3-large-patch-sweep-corrected/12b/split_offload_b1_l2048",
    "runtime_hbm_headroom_gb_aggregate": 18.253981696,
    "runtime_hbm_limit_gb_aggregate": 67.637338112,
    "runtime_peak_hbm_gb_aggregate": 49.383356416,
    "second_step_time_sec": "100.86366131799969",
    "status": "ok",
    "steps_recorded": 2,
    "tpu": "v5litepod-4",
    "valid_tokens_per_sec_excl_first": 0.6146911503096086,
    "variant": "split_offload",
    "wall_time_sec": 247.89425980199985,
    "xla_report": "/tmp/gemma3-large-patch-sweep-corrected/12b/split_offload_b1_l2048/xla/module_1031.jit__train_step.cl_914450892.after_optimizations-memory-usage-report.txt",
    "xla_train_step_gib_per_chip": 13.67
  },
  {
    "batch_size": 1,
    "chips": 4,
    "failure_type": "compile_oom",
    "lora_rank": 16,
    "max_length": 2048,
    "max_steps": 2,
    "mesh_fsdp": 4,
    "mesh_tp": 1,
    "model_id": "google/gemma-3-12b-it",
    "model_size": "12b",
    "oom_exceeded_gib": "6.13",
    "oom_limit_gib": "15.75",
    "oom_used_gib": "21.88",
    "requested_autopatch": true,
    "run_dir": "/tmp/gemma3-large-patch-sweep-corrected/12b/splash_b1_l2048",
    "status": "failed",
    "tpu": "v5litepod-4",
    "variant": "splash",
    "xla_report": "/tmp/gemma3-large-patch-sweep-corrected/12b/splash_b1_l2048/xla/module_0676.jit__train_step.cl_914450892.after_optimizations-memory-usage-report.txt",
    "xla_train_step_gib_per_chip": 21.88
  },
  {
    "autopatch_effective": true,
    "batch_size": 1,
    "cce_installed": true,
    "chips": 4,
    "default_ce": false,
    "final_loss": 1.839585542678833,
    "first_step_time_sec": "80.107969185",
    "gemma3_activation_policy_installed": true,
    "gemma3_splash_attention_installed": true,
    "gemma3_tiled_mlp_installed": true,
    "lora_rank": 16,
    "loss_tokens_per_sec_excl_first": 0.34743140229258607,
    "max_length": 2048,
    "max_steps": 2,
    "mean_loss": 2.173102855682373,
    "mean_step_time_sec_excl_first": 71.95665053599987,
    "mesh_fsdp": 4,
    "mesh_tp": 1,
    "model_id": "google/gemma-3-12b-it",
    "model_size": "12b",
    "requested_autopatch": true,
    "run_dir": "/tmp/gemma3-large-patch-sweep-corrected/12b/stacked_b1_l2048",
    "runtime_hbm_headroom_gb_aggregate": 19.710353408,
    "runtime_hbm_limit_gb_aggregate": 67.637338112,
    "runtime_peak_hbm_gb_aggregate": 47.926984704,
    "second_step_time_sec": "71.95665053599987",
    "status": "ok",
    "steps_recorded": 2,
    "tpu": "v5litepod-4",
    "valid_tokens_per_sec_excl_first": 0.8616298776856135,
    "variant": "stacked",
    "wall_time_sec": 186.70497460800016,
    "xla_report": "/tmp/gemma3-large-patch-sweep-corrected/12b/stacked_b1_l2048/xla/module_0997.jit__train_step.cl_914450892.after_optimizations-memory-usage-report.txt",
    "xla_train_step_gib_per_chip": 11.77
  },
  {
    "autopatch_effective": true,
    "batch_size": 1,
    "cce_installed": true,
    "chips": 4,
    "default_ce": false,
    "final_loss": 1.7074103355407715,
    "first_step_time_sec": "98.58096055399983",
    "gemma3_activation_policy_installed": true,
    "gemma3_splash_attention_installed": true,
    "gemma3_tiled_mlp_installed": true,
    "lora_rank": 16,
    "loss_tokens_per_sec_excl_first": 0.2815063366034518,
    "max_length": 4096,
    "max_steps": 2,
    "mean_loss": 2.1169501543045044,
    "mean_step_time_sec_excl_first": 88.80794763499989,
    "mesh_fsdp": 4,
    "mesh_tp": 1,
    "model_id": "google/gemma-3-12b-it",
    "model_size": "12b",
    "requested_autopatch": true,
    "run_dir": "/tmp/gemma3-large-patch-sweep-corrected/12b/stacked_b1_l4096",
    "runtime_hbm_headroom_gb_aggregate": 19.558291456,
    "runtime_hbm_limit_gb_aggregate": 67.637338112,
    "runtime_peak_hbm_gb_aggregate": 48.079046656,
    "second_step_time_sec": "88.80794763499989",
    "status": "ok",
    "steps_recorded": 2,
    "tpu": "v5litepod-4",
    "valid_tokens_per_sec_excl_first": 0.6981357147765604,
    "variant": "stacked",
    "wall_time_sec": 223.26168510800017,
    "xla_report": "/tmp/gemma3-large-patch-sweep-corrected/12b/stacked_b1_l4096/xla/module_1076.jit__train_step.cl_914450892.after_optimizations-memory-usage-report.txt",
    "xla_train_step_gib_per_chip": 14.42
  },
  {
    "batch_size": 1,
    "chips": 4,
    "failure_type": "compile_oom",
    "lora_rank": 16,
    "max_length": 8192,
    "max_steps": 2,
    "mesh_fsdp": 4,
    "mesh_tp": 1,
    "model_id": "google/gemma-3-12b-it",
    "model_size": "12b",
    "oom_exceeded_gib": "2.06",
    "oom_limit_gib": "15.75",
    "oom_used_gib": "17.80",
    "requested_autopatch": true,
    "run_dir": "/tmp/gemma3-large-patch-sweep-corrected/12b/stacked_b1_l8192",
    "status": "failed",
    "tpu": "v5litepod-4",
    "variant": "stacked",
    "xla_report": "/tmp/gemma3-large-patch-sweep-corrected/12b/stacked_b1_l8192/xla/module_0767.jit__train_step.cl_914450892.after_optimizations-memory-usage-report.txt",
    "xla_train_step_gib_per_chip": 17.8
  }
]
